{"cameraMode":{"drawMode":0,"name":"Shaded","section":"Shading Mode"},"sceneLighting":false,"audioPlay":false,"sceneViewState":{"m_AlwaysRefresh":false,"showFog":true,"showSkybox":true,"showFlares":true,"showImageEffects":true,"showParticleSystems":true,"showVisualEffectGraphs":true,"m_FxEnabled":true},"in2DMode":false,"pivot":{"x":-4.161741256713867,"y":-3.1509246826171877,"z":66.56396484375},"rotation":{"x":-0.5405928492546082,"y":0.038330670446157458,"z":-0.024666678160429,"w":-0.840049147605896},"size":19.938766479492189,"orthographic":false}